aliyun_img_utils/__init__.py
aliyun_img_utils/aliyun_cli.py
aliyun_img_utils/aliyun_exceptions.py
aliyun_img_utils/aliyun_image.py
aliyun_img_utils/aliyun_utils.py
aliyun_img_utils-2.5.1.dist-info/licenses/LICENSE
aliyun_img_utils-2.5.1.dist-info/METADATA
aliyun_img_utils-2.5.1.dist-info/WHEEL
aliyun_img_utils-2.5.1.dist-info/entry_points.txt
aliyun_img_utils-2.5.1.dist-info/top_level.txt
aliyun_img_utils-2.5.1.dist-info/RECORD
