Metadata-Version: 2.4
Name: aliyun-img-utils
Version: 2.5.1
Summary: Package that provides utilities for handling images in Aliyun Cloud.
Home-page: https://github.com/SUSE-Enceladus/aliyun-img-utils
Author: SUSE
Author-email: public-cloud-dev@susecloud.net
License: GPLv3+
Keywords: aliyun-img-utils aliyun_img_utils
Classifier: Development Status :: 4 - Beta
Classifier: Environment :: Console
Classifier: Intended Audience :: Developers
Classifier: Topic :: System :: Software Distribution
Classifier: License :: OSI Approved :: GNU General Public License v3 or later (GPLv3+)
Classifier: Natural Language :: English
Classifier: Programming Language :: Python :: 3
Classifier: Programming Language :: Python :: 3.8
Classifier: Programming Language :: Python :: 3.9
Classifier: Programming Language :: Python :: 3.10
Classifier: Programming Language :: Python :: 3.11
Classifier: Programming Language :: Python :: 3.12
Requires-Python: >=3.8
License-File: LICENSE
Requires-Dist: click
Requires-Dist: oss2
Requires-Dist: PyYAML
Requires-Dist: aliyun-python-sdk-core
Requires-Dist: aliyun-python-sdk-ecs>=4.24.77
Requires-Dist: python-dateutil
Provides-Extra: dev
Requires-Dist: coverage; extra == "dev"
Requires-Dist: flake8; extra == "dev"
Requires-Dist: pytest-cov; extra == "dev"
Requires-Dist: bumpversion; extra == "dev"
Requires-Dist: pip>=7.0.0; extra == "dev"
Provides-Extra: test
Requires-Dist: coverage; extra == "test"
Requires-Dist: flake8; extra == "test"
Requires-Dist: pytest-cov; extra == "test"
Dynamic: author
Dynamic: author-email
Dynamic: classifier
Dynamic: description
Dynamic: description-content-type
Dynamic: home-page
Dynamic: keywords
Dynamic: license
Dynamic: license-file
Dynamic: provides-extra
Dynamic: requires-dist
Dynamic: requires-python
Dynamic: summary
